droots-0.1.3.dist-info/licenses/LICENSE
drt/__init__.py
drt/__main__.py
drt/argparser.py
drt/cli.py
drt/config.py
drt/constructor.py
drt/helper.py
drt/sanitize.py
drt/templates/__init__.py
drt/templates/autotest.py
drt/templates/main.py
drt/templates/nonpies.py
drt/templates/utils.py
droots-0.1.3.dist-info/METADATA
droots-0.1.3.dist-info/WHEEL
droots-0.1.3.dist-info/entry_points.txt
droots-0.1.3.dist-info/top_level.txt
droots-0.1.3.dist-info/RECORD
