Metadata-Version: 2.4
Name: Droots
Version: 0.1.3
Summary: Generate structured Python project folders instantly
Author-email: "Caleb M. Sibanda" <darkian.dev@gmail.com>
License: MIT
Requires-Python: >=3.10
License-File: LICENSE
Dynamic: license-file
